bert_qa/__init__.py
bert_qa/activations.py
bert_qa/albert_transformer_encoder.py
bert_qa/attention.py
bert_qa/bert_classifier.py
bert_qa/bert_modeling.py
bert_qa/bert_models.py
bert_qa/bert_pretrainer.py
bert_qa/bert_span_labeler.py
bert_qa/classification.py
bert_qa/classifier_data_lib.py
bert_qa/cloud_lib.py
bert_qa/dense_einsum.py
bert_qa/distribution_utils.py
bert_qa/hooks.py
bert_qa/hooks_helper.py
bert_qa/input_pipeline.py
bert_qa/keras_utils.py
bert_qa/logger.py
bert_qa/masked_lm.py
bert_qa/masked_softmax.py
bert_qa/metric_hook.py
bert_qa/model_saving_utils.py
bert_qa/model_training_utils.py
bert_qa/on_device_embedding.py
bert_qa/optimization.py
bert_qa/position_embedding.py
bert_qa/self_attention_mask.py
bert_qa/span_labeling.py
bert_qa/squad.py
bert_qa/squad_lib.py
bert_qa/squad_lib_sp.py
bert_qa/tf_utils.py
bert_qa/tokenization.py
bert_qa/tpu_lib.py
bert_qa/transformer.py
bert_qa/transformer_encoder.py
bert_qa/weighted_sparse_categorical_crossentropy.py
bert_qa-0.1.0.dist-info/LICENSE
bert_qa-0.1.0.dist-info/METADATA
bert_qa-0.1.0.dist-info/WHEEL
bert_qa-0.1.0.dist-info/top_level.txt
bert_qa-0.1.0.dist-info/RECORD
