Metadata-Version: 2.1
Name: bert-qa
Version: 0.1.0
Summary: Question-Answering system using state-of-the-art pre-trained language models.
Home-page: https://github.com/artitw/BERT_QA
Author: Artit Wangperawong
Author-email: artitw@gmail.com
License: UNKNOWN
Keywords: bert nlp text squad data science machine learning
Platform: UNKNOWN
Classifier: Programming Language :: Python :: 3
Classifier: License :: OSI Approved :: Apache Software License
Classifier: Operating System :: OS Independent
Requires-Dist: sentencepiece
Requires-Dist: tensorflow (>=2.0.0)
Requires-Dist: tensorflow-gpu (>=2.0.0)
Requires-Dist: tensorflow-hub (>=0.6.0)
